lilbio/__init__.py
lilbio/bioparsers.py
lilbio/funcs.py
lilbio/lilbio_utils.py
lilbio/parser.py
little_bio_parser-0.8.3.dist-info/LICENSE.txt
little_bio_parser-0.8.3.dist-info/METADATA
little_bio_parser-0.8.3.dist-info/WHEEL
little_bio_parser-0.8.3.dist-info/top_level.txt
little_bio_parser-0.8.3.dist-info/RECORD
