Metadata-Version: 2.1
Name: little-bio-parser
Version: 0.8.3
Summary: A template project with packages
Home-page: https://github.com/simomarsili/little-bio-parser
Author: Simone Marsili
Author-email: simo.marsili@gmail.com
License: BSD 3-Clause
Platform: UNKNOWN
Classifier: Development Status :: 3 - Alpha
Classifier: License :: OSI Approved :: BSD License
Classifier: Programming Language :: Python :: 3
Classifier: Programming Language :: Python :: 3.4
Classifier: Programming Language :: Python :: 3.5
Classifier: Programming Language :: Python :: 3.6
Requires-Dist: gopen (>=0.6)
Provides-Extra: test
Requires-Dist: pytest ; extra == 'test'
